examples/circuitpython/test_bar.py
examples/circuitpython/test_matrix.py
examples/circuitpython/test_matrixcolour.py
examples/circuitpython/test_matrixfeatherwing.py
examples/circuitpython/test_matrixmulti.py
examples/circuitpython/test_segment.py
examples/circuitpython/test_segment14_adafruit_054in.py
examples/circuitpython/test_segment14_ecbuying_054in.py
examples/circuitpython/test_segment14_sparkfun_alpha.py
examples/circuitpython/test_segmentbig.py
examples/circuitpython/test_segmentgen-01.py
examples/circuitpython/test_segmentgen-02.py
examples/micropython/test_bar.py
examples/micropython/test_matrix.py
examples/micropython/test_matrixcolour.py
examples/micropython/test_matrixfeatherwing.py
examples/micropython/test_matrixmulti.py
examples/micropython/test_segment.py
examples/micropython/test_segment14_adafruit_054in.py
examples/micropython/test_segment14_ecbuying_054.py
examples/micropython/test_segment14_sparkfun_alpha.py
examples/micropython/test_segmentbig.py
examples/micropython/test_segmentgen-01.py
examples/micropython/test_segmentgen-02.py
ht16k33/__init__.py
ht16k33/ht16k33.py
ht16k33/ht16k33bar.py
ht16k33/ht16k33matrix.py
ht16k33/ht16k33matrixcolour.py
ht16k33/ht16k33matrixfeatherwing.py
ht16k33/ht16k33matrixmulti.py
ht16k33/ht16k33segment.py
ht16k33/ht16k33segment14.py
ht16k33/ht16k33segmentbig.py
ht16k33/ht16k33segmentgen.py
tools/colour-glyph-maker.py
ht16k33_python-4.2.0.dist-info/LICENSE.md
ht16k33_python-4.2.0.dist-info/METADATA
ht16k33_python-4.2.0.dist-info/WHEEL
ht16k33_python-4.2.0.dist-info/top_level.txt
ht16k33_python-4.2.0.dist-info/RECORD
