Metadata-Version: 2.2
Name: ht16k33-python
Version: 4.2.0
Summary: MicroPython and CircuitPython library for HT16K33 LED matrices and segment displays.
Author: Ubi de Feo, Sebastian Romero, akbiocca
Author-email: Tony Smith <support@smittytone.net>
Maintainer-email: Tony Smith <support@smittytone.net>
License: MIT
Project-URL: Homepage, https://github.com/smittytone/HT16K33-Python
Keywords: ht16k33,vk16k33,led,matrix,segment,bar graph,displays,hardware,micropython,circuitpython
Classifier: Intended Audience :: Developers
Classifier: Topic :: Software Development :: Libraries
Classifier: Topic :: Software Development :: Embedded Systems
Classifier: Topic :: System :: Hardware
Classifier: License :: OSI Approved :: MIT License
Classifier: Programming Language :: Python :: 3
License-File: LICENSE.md
